django_deploy_templates/__init__.py
django_deploy_templates/apps.py
django_deploy_templates/tests.py
django_deploy_templates/management/__init__.py
django_deploy_templates/management/commands/__init__.py
django_deploy_templates/management/commands/generate_config.py
django_deploy_templates-0.1.1.dist-info/METADATA
django_deploy_templates-0.1.1.dist-info/WHEEL
django_deploy_templates-0.1.1.dist-info/top_level.txt
django_deploy_templates-0.1.1.dist-info/RECORD
