Metadata-Version: 2.1
Name: django-deploy-templates
Version: 0.1.1
Summary: UNKNOWN
Home-page: UNKNOWN
License: UNKNOWN
Platform: UNKNOWN
Requires-Dist: Django (>=2)
Requires-Dist: Jinja2 (>=2.10)
